{
  "openapi": "3.0.0",
  "info": {
    "title": "My API",
    "version": "1.0.0",
    "description": "API documentation using ReDoc"
  },
  "servers": [
    {
      "url": "http://localhost:3000",
      "description": "Development server"
    }
  ],
  "paths": {
    "/api/v1/yields": {
      "get": {
        "summary": "Lấy danh sách tất cả yields",
        "tags": [
          "Yields"
        ],
        "responses": {
          "200": {
            "description": "Danh sách yields",
            "content": {
              "application/json": {
                "schema": {
                  "type": "array",
                  "items": {
                    "$ref": "#/components/schemas/Yield"
                  }
                }
              }
            }
          },
          "400": {
            "description": "Tham số không hợp lệ",
            "content": {
              "application/json": {
                "schema": {
                  "$ref": "#/components/schemas/ErrorResponse"
                }
              }
            }
          },
          "500": {
            "description": "Lỗi hệ thống",
            "content": {
              "application/json": {
                "schema": {
                  "$ref": "#/components/schemas/ErrorResponse"
                }
              }
            }
          },
          "502": {
            "description": "Lỗi từ API bên ngoài",
            "content": {
              "application/json": {
                "schema": {
                  "$ref": "#/components/schemas/ErrorResponse"
                }
              }
            }
          }
        }
      }
    },
    "/api/v1/yields/{symbol}": {
      "get": {
        "summary": "Lấy yield theo symbol",
        "tags": [
          "Yields"
        ],
        "parameters": [
          {
            "in": "path",
            "name": "symbol",
            "required": true,
            "description": "Symbol của yield",
            "schema": {
              "type": "string"
            }
          }
        ],
        "responses": {
          "200": {
            "description": "Yield tìm thấy",
            "content": {
              "application/json": {
                "schema": {
                  "$ref": "#/components/schemas/Yield"
                }
              }
            }
          },
          "400": {
            "description": "Tham số không hợp lệ",
            "content": {
              "application/json": {
                "schema": {
                  "$ref": "#/components/schemas/ErrorResponse"
                }
              }
            }
          },
          "404": {
            "description": "Không tìm thấy yield",
            "content": {
              "application/json": {
                "schema": {
                  "$ref": "#/components/schemas/ErrorResponse"
                }
              }
            }
          },
          "500": {
            "description": "Lỗi hệ thống",
            "content": {
              "application/json": {
                "schema": {
                  "$ref": "#/components/schemas/ErrorResponse"
                }
              }
            }
          },
          "502": {
            "description": "Lỗi từ API bên ngoài",
            "content": {
              "application/json": {
                "schema": {
                  "$ref": "#/components/schemas/ErrorResponse"
                }
              }
            }
          }
        }
      }
    }
  },
  "components": {
    "schemas": {
      "Yield": {
        "type": "object",
        "properties": {
          "symbol": {
            "type": "string",
            "description": "Symbol của yield"
          },
          "apy": {
            "type": "number",
            "description": "Annual Percentage Yield"
          },
          "updatedAt": {
            "type": "string",
            "format": "date-time",
            "description": "Ngày cập nhật"
          }
        }
      },
      "ErrorResponse": {
        "type": "object",
        "properties": {
          "success": {
            "type": "boolean",
            "example": false
          },
          "code": {
            "type": "integer",
            "example": 1001
          },
          "msg": {
            "type": "string",
            "example": "Resource not found"
          },
          "data": {
            "type": "object",
            "properties": {
              "message": {
                "type": "string"
              },
              "path": {
                "type": "string"
              },
              "method": {
                "type": "string"
              },
              "timestamp": {
                "type": "string",
                "format": "date-time"
              }
            }
          }
        }
      }
    }
  },
  "tags": []
}